setup.py
gskiranadipkg/__init__.py
gskiranadipkg/calculator.py
gskiranadipkg.egg-info/PKG-INFO
gskiranadipkg.egg-info/SOURCES.txt
gskiranadipkg.egg-info/dependency_links.txt
gskiranadipkg.egg-info/top_level.txt