Metadata-Version: 2.1
Name: gskiranadipkg
Version: 0.0.1
Summary: ADI python module
Home-page: https://github.com/SaikiranGudla/mydemopackage
Author: saikiran_g
Author-email: saikiran5955@gmail.com
Classifier: Programming Language :: Python :: 3
Classifier: Operating System :: OS Independent
